hack4u/__init__.py
hack4u/courses.py
hack4u/utils.py
MiPaquetito-0.0.1.dist-info/METADATA
MiPaquetito-0.0.1.dist-info/WHEEL
MiPaquetito-0.0.1.dist-info/top_level.txt
MiPaquetito-0.0.1.dist-info/RECORD
