Metadata-Version: 2.1
Name: MiPaquetito
Version: 0.0.1
Summary: Una Biblioteca para poder ver mi pequeña Python
Home-page: https://epsaind.dev
Author: Epsaind dev
